mlflow_toolkit/__init__.py
mlflow_toolkit/utils.py
mlflow_toolkit/worker.py
mlflow_toolkit-0.2.0.dist-info/licenses/LICENSE
mlflow_toolkit-0.2.0.dist-info/WHEEL
mlflow_toolkit-0.2.0.dist-info/METADATA
mlflow_toolkit-0.2.0.dist-info/RECORD
