Metadata-Version: 2.4
Name: mlflow-toolkit
Version: 0.2.0
Summary: 
Author-email: Dubovik Pavel <geometryk@gmail.com>
Requires-Python: >=3.7
License-File: LICENSE
Requires-Dist: mlflow
Requires-Dist: PyYAML
Requires-Dist: dill ; extra == "extras"
Requires-Dist: joblib ; extra == "extras"
Project-URL: Homepage, https://github.com/dubovikmaster/mlflow-toolkit
Provides-Extra: extras
